pykemonGo/__init__.py
pykemonGo/__main__.py
pykemonGo/pykemonASCII.py
pykemonGo-1.0.0.dist-info/LICENSE
pykemonGo-1.0.0.dist-info/METADATA
pykemonGo-1.0.0.dist-info/WHEEL
pykemonGo-1.0.0.dist-info/entry_points.txt
pykemonGo-1.0.0.dist-info/top_level.txt
pykemonGo-1.0.0.dist-info/RECORD
