Metadata-Version: 2.1
Name: pykemonGo
Version: 1.0.0
Summary: Package built with pypi to print images of pokemon
Author-email: Group GGWP <swp6940@gmail.com>
License: GNU GENERAL PUBLIC LICENSE
Project-URL: Homepage, https://github.com/software-students-fall2023/3-python-package-exercise-ggwp
Project-URL: Repository, https://github.com/software-students-fall2023/3-python-package-exercise-ggwp.git
Project-URL: Bug Tracker, https://github.com/software-students-fall2023/3-python-package-exercise-ggwp/issues
Keywords: python,package,build,tutorial
Classifier: Programming Language :: Python :: 3
Classifier: Intended Audience :: Education
Classifier: License :: OSI Approved :: GNU General Public License v3 (GPLv3)
Classifier: Operating System :: OS Independent
Requires-Python: >=3.7
License-File: LICENSE
Provides-Extra: dev
Requires-Dist: pytest ; extra == 'dev'
